url_request_scheduler/__init__.py
url_request_scheduler/request.py
url_request_scheduler/urs_request.py
url_request_scheduler-0.3.dist-info/METADATA
url_request_scheduler-0.3.dist-info/WHEEL
url_request_scheduler-0.3.dist-info/top_level.txt
url_request_scheduler-0.3.dist-info/RECORD
